setup.py
aiobroker/__init__.py
aiobroker/common.py
aiobroker/core.py
aiobroker/exceptions.py
aiobroker/queue.py
aiobroker.egg-info/PKG-INFO
aiobroker.egg-info/SOURCES.txt
aiobroker.egg-info/dependency_links.txt
aiobroker.egg-info/top_level.txt