Metadata-Version: 1.2
Name: aiobroker
Version: 0.4
Summary: Message broker to organize the communication of components with each other
Home-page: https://github.com/Fatal1ty/aiobroker
Author: Alexander Tikhonov
Author-email: random.gauss@gmail.com
License: Apache License, Version 2.0
Platform: all
Classifier: License :: OSI Approved :: Apache Software License
Classifier: Intended Audience :: Developers
Classifier: Programming Language :: Python :: 3 :: Only
Classifier: Programming Language :: Python :: 3.6
Classifier: Programming Language :: Python :: 3.7
Classifier: Development Status :: 4 - Beta
Requires-Python: >=3.6
